{"stem":"announc","instances":[{"docId":"370215KFa","docUri":"370215KFa.html","score":1,"contexts":[{"form":"announcement","weight":"1","pos":1113,"context":"...gain the agreement of Francis I. 9. Concerning the <mark>announcement<\/mark> of the (Imperial) Chamber Court dealing with...","fid":"letterContent"}]},{"docId":"A050","docUri":"A050.html","score":1,"contexts":[{"form":"announced","weight":"1","pos":377,"context":"...St. Margaret's Day was poorly attended, he has <mark>announced<\/mark> another one on St. Martin's Day in Nuremberg....","fid":"letterContent"}]}]}