{"stem":"bevelhen","instances":[{"docId":"370117FKa","docUri":"370117FKa.html","score":1,"contexts":[{"form":"bevelhen","weight":"1","pos":314,"context":"...E. L. unnd kay. M. bruederlich unnd freunndtlich <mark>bevelhen<\/mark>. Geben in unnser stat Wienn, denn siebentzehenten...","fid":"letterContent"}]},{"docId":"370228KFb","docUri":"370228KFb.html","score":1,"contexts":[{"form":"bevelhen","weight":"1","pos":537,"context":"...unnser stat auch fur sich selbs unserm kaiserlichen camerprocuratorfiscal <mark>bevelhen<\/mark>, wider solche verprecher und ungehorsamen, auf die...","fid":"letterContent"}]}]}