{"stem":"droht","instances":[{"docId":"370228KFb","docUri":"370228KFb.html","score":1,"contexts":[{"form":"droht","weight":"1","pos":91,"context":"..., die dem Reich wegen der Auseinandersetzung mit Frankreich <mark>droht<\/mark>, gesehen. Verweist auf das französische Schreiben....","fid":"letterContent"}]},{"docId":"A076","docUri":"A076.html","score":1,"contexts":[{"form":"droht","weight":"1","pos":192,"context":"...ihrer Schwester Maria das Schicksal der Kgin von Dänemark <mark>droht<\/mark>. 30. Die Stimme des Böhmenkgs ist ihm sicher...","fid":"letterContent"}]}]}