{"stem":"feray","instances":[{"docId":"370204FMa","docUri":"370204FMa.html","score":1,"contexts":[{"form":"feray","weight":"1","pos":957,"context":"...De reste, des nouvelles de ce quartier ne <mark>feray<\/mark> ycy redite, puis vous advertis de main de...","fid":"letterContent"}]},{"docId":"370215KFa","docUri":"370215KFa.html","score":1,"contexts":[{"form":"feray","weight":"1","pos":3259,"context":"..., et apres les luy envoyer seurement, n’en <mark>feray<\/mark> icy redictes. ","fid":"letterContent"}]}]}