{"stem":"januari","instances":[{"docId":"A189","docUri":"A189.html","score":1,"contexts":[{"form":"January","weight":"1","pos":66,"context":"1. Has received F's letters dated <mark>January<\/mark> 31, February 2 and March 1. 2. State Diet...","fid":"letterContent"}]},{"docId":"370228KFa","docUri":"370228KFa.html","score":1,"contexts":[{"form":"January","weight":"1","pos":150,"context":"...confirms the receipt of n.*370117FChb of 1 <mark>January<\/mark> 1537. K is pleased with F’s response to...","fid":"letterContent"}]},{"docId":"370215KFa","docUri":"370215KFa.html","score":1,"contexts":[{"form":"January","weight":"1","pos":488,"context":"...16 December 1536 and *370108FK of 8 <mark>January<\/mark> 1537, which arrived via Genoa. 2. K acknowledges...","fid":"letterContent"}]},{"docId":"A183","docUri":"A183.html","score":1,"contexts":[{"form":"January","weight":"1","pos":30,"context":"1. Has received Mg's letter dated <mark>January<\/mark> 29 with news of peace. Messages from Venice...","fid":"letterContent"}]},{"docId":"370117FKa","docUri":"370117FKa.html","score":1,"contexts":[{"form":"january","weight":"1","pos":321,"context":"...unnser stat Wienn, denn siebentzehenten tag des monats <mark>january<\/mark> anno etc. im sibenunnddreyssigisten, unnserer reiche der...","fid":"letterContent"}]},{"docId":"A072","docUri":"A072.html","score":1,"contexts":[{"form":"January","weight":"1","pos":71,"context":"1. Has received K's letters from December, <mark>January<\/mark> and March 3. Is pleased that Fuentarabias has been...","fid":"letterContent"}]},{"docId":"370228KFb","docUri":"370228KFb.html","score":1,"contexts":[{"form":"January","weight":"1","pos":144,"context":"...letter (probably n. *370117FCKb of 17 <mark>January<\/mark> 1537) and of the enclosed documents. He...","fid":"letterContent"}]},{"docId":"A178","docUri":"A178.html","score":1,"contexts":[{"form":"January","weight":"1","pos":33,"context":"1. Has received Mg's letters dated <mark>January<\/mark> 19 and 20 containing word of the Queen of...","fid":"letterContent"}]},{"docId":"A062","docUri":"A062.html","score":1,"contexts":[{"form":"January","weight":"1","pos":116,"context":"...1. Has received F's letters dated December 18 and <mark>January<\/mark> 13. 2. Thanks F for his support on behalf...","fid":"letterContent"}]},{"docId":"A057","docUri":"A057.html","score":1,"contexts":[{"form":"January","weight":"1","pos":85,"context":"Received L's letter of <mark>January<\/mark>, 14th and learned with great satisfaction what measures...","fid":"letterContent"}]}]}