{"stem":"pieper","instances":[{"docId":"370228KFa","docUri":"370228KFa.html","score":1,"contexts":[{"form":"Pieper","weight":"1","pos":792,"context":"...: Nuntiaturberichte I\/2, 3, 7; vgl. dazu auch <mark>Pieper<\/mark>: Zur Entstehungsgeschichte der ständigen Nuntiaturen, 104 und...","fid":"letterContent"}]},{"docId":"370215KFa","docUri":"370215KFa.html","score":1,"contexts":[{"form":"Pieper","weight":"1","pos":4244,"context":"...der alleinige päpstliche Vertreter beim Kaiser, vgl. <mark>Pieper<\/mark>: Zur Entstehungsgeschichte der ständigen Nuntiaturen, 94-96.","fid":"letterContent"}]}]}