{"stem":"publish","instances":[{"docId":"A038","docUri":"A038.html","score":1,"contexts":[{"form":"published","weight":"1","pos":268,"context":"...prior to any decision. 13. The commissioners have <mark>published<\/mark> the declaration that creditors shall wait four months in...","fid":"letterContent"}]},{"docId":"370228KFb","docUri":"370228KFb.html","score":1,"contexts":[{"form":"published","weight":"1","pos":237,"context":"...has had new mandates printed which are to be <mark>published<\/mark> if required. The Count of Ortenburg (Gabriel...","fid":"letterContent"}]}]}