{"stem":"senat","instances":[{"docId":"A166","docUri":"A166.html","score":1,"contexts":[{"form":"senat","weight":"1","pos":449,"context":"...cellui dud. Milan fit convocquer et appeller le <mark>senat<\/mark>, affin qu’ilz fussent tesmoings de la culpe que...","fid":"letterContent"}]},{"docId":"370215KFa","docUri":"370215KFa.html","score":1,"contexts":[{"form":"Senats","weight":"1","pos":5816,"context":"...Medici, 68). Daraufhin hatten die Mitglieder des florentinischen <mark>Senats<\/mark> mit kaiserlicher Intervention am 9. 1. 1537 Cosimo I....","fid":"letterContent"}]}]}