{"stem":"verursacht","instances":[{"docId":"370228KFb","docUri":"370228KFb.html","score":1,"contexts":[{"form":"verursacht","weight":"1","pos":670,"context":"...yezu disem krieg durch den konig von Franckhreich hohlich <mark>verursacht<\/mark> und gedrungen worden und unnsers teils an keinem leidlichen...","fid":"letterContent"}]},{"docId":"A051","docUri":"A051.html","score":1,"contexts":[{"form":"verursacht","weight":"1","pos":16,"context":"...er die Verzögerung im Abschlusse des Friedens mit Venedig <mark>verursacht<\/mark> habe. Er ist sowohl ihm wie K ein treuer...","fid":"letterContent"}]}]}